{"nodes": [{"id": "milestone_01_01_summary_app_shell_bootstrap_summary", "label": "01-01-SUMMARY: App Shell Bootstrap Summary", "file_type": "document", "source_file": ".planning/milestones/v1.0-phases/01-app-shell/01-01-SUMMARY.md", "source_location": null, "source_url": null, "captured_at": null, "author": null, "contributor": null}, {"id": "milestone_01_01_summary_upsert_decision", "label": "ShellPreferenceStore UPSERT Decision", "file_type": "rationale", "source_file": ".planning/milestones/v1.0-phases/01-app-shell/01-01-SUMMARY.md", "source_location": null, "source_url": null, "captured_at": null, "author": null, "contributor": null, "rationale": "ShellPreferenceStore uses UPSERT (INSERT ON CONFLICT DO UPDATE) to avoid race between insert/update."}, {"id": "milestone_01_01_summary_savepoint_migration_decision", "label": "SAVEPOINT-based Migration Runner Decision", "file_type": "rationale", "source_file": ".planning/milestones/v1.0-phases/01-app-shell/01-01-SUMMARY.md", "source_location": null, "source_url": null, "captured_at": null, "author": null, "contributor": null, "rationale": "Migration runner uses SAVEPOINTs not outer transactions because SQLite forbids DDL in some transaction modes."}], "edges": [{"source": "milestone_01_01_summary_app_shell_bootstrap_summary", "target": "milestone_01_01_plan_app_shell_bootstrap_plan", "relation": "implements", "confidence": "EXTRACTED", "confidence_score": 1.0, "source_file": ".planning/milestones/v1.0-phases/01-app-shell/01-01-SUMMARY.md", "source_location": null, "weight": 1.0}, {"source": "milestone_01_01_summary_app_shell_bootstrap_summary", "target": "milestone_01_01_summary_upsert_decision", "relation": "references", "confidence": "EXTRACTED", "confidence_score": 1.0, "source_file": ".planning/milestones/v1.0-phases/01-app-shell/01-01-SUMMARY.md", "source_location": null, "weight": 1.0}, {"source": "milestone_01_01_summary_app_shell_bootstrap_summary", "target": "milestone_01_01_summary_savepoint_migration_decision", "relation": "references", "confidence": "EXTRACTED", "confidence_score": 1.0, "source_file": ".planning/milestones/v1.0-phases/01-app-shell/01-01-SUMMARY.md", "source_location": null, "weight": 1.0}, {"source": "milestone_01_01_summary_app_shell_bootstrap_summary", "target": "milestone_01_review_review_report", "relation": "references", "confidence": "INFERRED", "confidence_score": 0.85, "source_file": ".planning/milestones/v1.0-phases/01-app-shell/01-01-SUMMARY.md", "source_location": null, "weight": 1.0}], "hyperedges": []}