{"nodes": [{"id": "c_workspaces_desktop_ai_client_src_tauri_src_providers_routing_rs", "label": "routing.rs", "file_type": "code", "source_file": "src-tauri/src/providers/routing.rs", "source_location": "L1"}, {"id": "providers_routing_build_provider_messages", "label": "build_provider_messages()", "file_type": "code", "source_file": "src-tauri/src/providers/routing.rs", "source_location": "L27"}, {"id": "validatedmessage", "label": "ValidatedMessage", "file_type": "code", "source_file": "src-tauri/src/providers/routing.rs", "source_location": "L27"}, {"id": "vec", "label": "Vec", "file_type": "code", "source_file": "src-tauri/src/providers/routing.rs", "source_location": "L27"}, {"id": "providermessage", "label": "ProviderMessage", "file_type": "code", "source_file": "src-tauri/src/providers/routing.rs", "source_location": "L27"}, {"id": "providers_routing_user_msg", "label": "user_msg()", "file_type": "code", "source_file": "src-tauri/src/providers/routing.rs", "source_location": "L54"}, {"id": "providers_routing_assistant_msg", "label": "assistant_msg()", "file_type": "code", "source_file": "src-tauri/src/providers/routing.rs", "source_location": "L61"}, {"id": "providers_routing_build_provider_messages_prepends_system_prompt", "label": "build_provider_messages_prepends_system_prompt()", "file_type": "code", "source_file": "src-tauri/src/providers/routing.rs", "source_location": "L69"}, {"id": "providers_routing_build_provider_messages_preserves_order", "label": "build_provider_messages_preserves_order()", "file_type": "code", "source_file": "src-tauri/src/providers/routing.rs", "source_location": "L78"}], "edges": [{"source": "c_workspaces_desktop_ai_client_src_tauri_src_providers_routing_rs", "target": "providermessage", "relation": "imports_from", "confidence": "EXTRACTED", "source_file": "src-tauri/src/providers/routing.rs", "source_location": "L16", "weight": 1.0, "context": "import"}, {"source": "c_workspaces_desktop_ai_client_src_tauri_src_providers_routing_rs", "target": "validatedmessage", "relation": "imports_from", "confidence": "EXTRACTED", "source_file": "src-tauri/src/providers/routing.rs", "source_location": "L17", "weight": 1.0, "context": "import"}, {"source": "c_workspaces_desktop_ai_client_src_tauri_src_providers_routing_rs", "target": "providers_routing_build_provider_messages", "relation": "contains", "confidence": "EXTRACTED", "source_file": "src-tauri/src/providers/routing.rs", "source_location": "L27", "weight": 1.0}, {"source": "providers_routing_build_provider_messages", "target": "validatedmessage", "relation": "references", "confidence": "EXTRACTED", "source_file": "src-tauri/src/providers/routing.rs", "source_location": "L27", "weight": 1.0, "context": "parameter_type"}, {"source": "providers_routing_build_provider_messages", "target": "vec", "relation": "references", "confidence": "EXTRACTED", "source_file": "src-tauri/src/providers/routing.rs", "source_location": "L27", "weight": 1.0, "context": "return_type"}, {"source": "providers_routing_build_provider_messages", "target": "providermessage", "relation": "references", "confidence": "EXTRACTED", "source_file": "src-tauri/src/providers/routing.rs", "source_location": "L27", "weight": 1.0, "context": "generic_arg"}, {"source": "c_workspaces_desktop_ai_client_src_tauri_src_providers_routing_rs", "target": "super", "relation": "imports_from", "confidence": "EXTRACTED", "source_file": "src-tauri/src/providers/routing.rs", "source_location": "L51", "weight": 1.0, "context": "import"}, {"source": "c_workspaces_desktop_ai_client_src_tauri_src_providers_routing_rs", "target": "role", "relation": "imports_from", "confidence": "EXTRACTED", "source_file": "src-tauri/src/providers/routing.rs", "source_location": "L52", "weight": 1.0, "context": "import"}, {"source": "c_workspaces_desktop_ai_client_src_tauri_src_providers_routing_rs", "target": "providers_routing_user_msg", "relation": "contains", "confidence": "EXTRACTED", "source_file": "src-tauri/src/providers/routing.rs", "source_location": "L54", "weight": 1.0}, {"source": "providers_routing_user_msg", "target": "validatedmessage", "relation": "references", "confidence": "EXTRACTED", "source_file": "src-tauri/src/providers/routing.rs", "source_location": "L54", "weight": 1.0, "context": "return_type"}, {"source": "c_workspaces_desktop_ai_client_src_tauri_src_providers_routing_rs", "target": "providers_routing_assistant_msg", "relation": "contains", "confidence": "EXTRACTED", "source_file": "src-tauri/src/providers/routing.rs", "source_location": "L61", "weight": 1.0}, {"source": "providers_routing_assistant_msg", "target": "validatedmessage", "relation": "references", "confidence": "EXTRACTED", "source_file": "src-tauri/src/providers/routing.rs", "source_location": "L61", "weight": 1.0, "context": "return_type"}, {"source": "c_workspaces_desktop_ai_client_src_tauri_src_providers_routing_rs", "target": "providers_routing_build_provider_messages_prepends_system_prompt", "relation": "contains", "confidence": "EXTRACTED", "source_file": "src-tauri/src/providers/routing.rs", "source_location": "L69", "weight": 1.0}, {"source": "c_workspaces_desktop_ai_client_src_tauri_src_providers_routing_rs", "target": "providers_routing_build_provider_messages_preserves_order", "relation": "contains", "confidence": "EXTRACTED", "source_file": "src-tauri/src/providers/routing.rs", "source_location": "L78", "weight": 1.0}, {"source": "providers_routing_build_provider_messages_prepends_system_prompt", "target": "providers_routing_user_msg", "relation": "calls", "context": "call", "confidence": "EXTRACTED", "source_file": "src-tauri/src/providers/routing.rs", "source_location": "L70", "weight": 1.0}, {"source": "providers_routing_build_provider_messages_prepends_system_prompt", "target": "providers_routing_build_provider_messages", "relation": "calls", "context": "call", "confidence": "EXTRACTED", "source_file": "src-tauri/src/providers/routing.rs", "source_location": "L71", "weight": 1.0}, {"source": "providers_routing_build_provider_messages_preserves_order", "target": "providers_routing_user_msg", "relation": "calls", "context": "call", "confidence": "EXTRACTED", "source_file": "src-tauri/src/providers/routing.rs", "source_location": "L80", "weight": 1.0}, {"source": "providers_routing_build_provider_messages_preserves_order", "target": "providers_routing_assistant_msg", "relation": "calls", "context": "call", "confidence": "EXTRACTED", "source_file": "src-tauri/src/providers/routing.rs", "source_location": "L81", "weight": 1.0}, {"source": "providers_routing_build_provider_messages_preserves_order", "target": "providers_routing_build_provider_messages", "relation": "calls", "context": "call", "confidence": "EXTRACTED", "source_file": "src-tauri/src/providers/routing.rs", "source_location": "L84", "weight": 1.0}], "raw_calls": [{"caller_nid": "providers_routing_build_provider_messages", "callee": "as_str", "is_member_call": true, "source_file": "C:\\workspaces\\desktop-ai-client\\src-tauri\\src\\providers\\routing.rs", "source_location": "L41"}]}